{
    "component_type": "style",
    "component_id": "wikindx",
    "component_version": "191",
    "component_builtin": "false",
    "component_updatable": "true",
    "component_name": "Wikindx",
    "component_description": "Wikindx Style",
    "component_licence": "ISC License",
    "component_website": "https://wikindx.sourceforge.io/",
    "component_authors": [
        {
            "author_name": "Mark Grimshaw-Aagaard",
            "author_role": "Compiler",
            "author_copyright": "2005, 2020",
            "author_email": "sirfragalot@users.sourceforge.net",
            "author_website": "https://vbn.aau.dk/en/persons/126217"
        }
    ],
    "component_sha256": "fab05b91335e6ff4a4c41794fbb4e7475c33602502853c265071e6317429b99b"
}